xmlsec/DataPrimitives.py
xmlsec/PyCryptoShim.py
xmlsec/__init__.py
xmlsec/constants.py
xmlsec/crypto.py
xmlsec/exceptions.py
xmlsec/int_to_bytes.py
xmlsec/pk11.py
xmlsec/tools.py
xmlsec/utils.py
xmlsec/test/__init__.py
xmlsec/test/case.py
xmlsec/test/p11_test.py
xmlsec/test/sign_verify_test.py
xmlsec/test/transform_test.py
xmlsec/test/util_test.py
pyXMLSecurity-0.30.dist-info/LICENSE.txt
pyXMLSecurity-0.30.dist-info/METADATA
pyXMLSecurity-0.30.dist-info/WHEEL
pyXMLSecurity-0.30.dist-info/entry_points.txt
pyXMLSecurity-0.30.dist-info/top_level.txt
pyXMLSecurity-0.30.dist-info/RECORD
