Metadata-Version: 2.1
Name: pyXMLSecurity
Version: 0.30
Summary: pure Python XML Security
Home-page: http://blogs.mnt.se
Author: Leif Johansson
Author-email: leifj@sunet.se
License: BSD
Keywords: xml xml-dsig security digital signature rsa
License-File: LICENSE.txt
Requires-Dist: defusedxml
Requires-Dist: lxml
Requires-Dist: pyconfig
Requires-Dist: requests
Requires-Dist: cryptography
Requires-Dist: six
Provides-Extra: pkcs11
Requires-Dist: PyKCS11 ; extra == 'pkcs11'
